[
  {
    "age_ann": 55,
    "results": [
      {
        "theta": 0.0,
        "age_ann": 55,
        "EU_mean": -4312056.408155986,
        "EW_mean": 0.46327406449248526,
        "n_paths": 150
      },
      {
        "theta": 0.2,
        "age_ann": 55,
        "EU_mean": -4219661.10664501,
        "EW_mean": 0.3752692830722948,
        "n_paths": 150
      },
      {
        "theta": 0.4,
        "age_ann": 55,
        "EU_mean": -4139532.488150033,
        "EW_mean": 0.28565295290738096,
        "n_paths": 150
      },
      {
        "theta": 0.6,
        "age_ann": 55,
        "EU_mean": -4060641.516233082,
        "EW_mean": 0.19377373173091314,
        "n_paths": 150
      }
    ],
    "theta_star": 0.6
  },
  {
    "age_ann": 56,
    "results": [
      {
        "theta": 0.0,
        "age_ann": 56,
        "EU_mean": -4312056.408155986,
        "EW_mean": 0.46327406449248526,
        "n_paths": 150
      },
      {
        "theta": 0.2,
        "age_ann": 56,
        "EU_mean": -4209412.131037975,
        "EW_mean": 0.37511483850803096,
        "n_paths": 150
      },
      {
        "theta": 0.4,
        "age_ann": 56,
        "EU_mean": -4117125.1539024804,
        "EW_mean": 0.2853900183509809,
        "n_paths": 150
      },
      {
        "theta": 0.6,
        "age_ann": 56,
        "EU_mean": -4025388.090863286,
        "EW_mean": 0.19347546648050457,
        "n_paths": 150
      }
    ],
    "theta_star": 0.6
  },
  {
    "age_ann": 57,
    "results": [
      {
        "theta": 0.0,
        "age_ann": 57,
        "EU_mean": -4312056.408155986,
        "EW_mean": 0.46327406449248526,
        "n_paths": 150
      },
      {
        "theta": 0.2,
        "age_ann": 57,
        "EU_mean": -4215637.863939016,
        "EW_mean": 0.3749471326788195,
        "n_paths": 150
      },
      {
        "theta": 0.4,
        "age_ann": 57,
        "EU_mean": -4126334.8082879907,
        "EW_mean": 0.28510481567577856,
        "n_paths": 150
      },
      {
        "theta": 0.6,
        "age_ann": 57,
        "EU_mean": -4035855.7928914134,
        "EW_mean": 0.19315230715838014,
        "n_paths": 150
      }
    ],
    "theta_star": 0.6
  },
  {
    "age_ann": 58,
    "results": [
      {
        "theta": 0.0,
        "age_ann": 58,
        "EU_mean": -4312056.408155986,
        "EW_mean": 0.46327406449248526,
        "n_paths": 150
      },
      {
        "theta": 0.2,
        "age_ann": 58,
        "EU_mean": -4212953.513093325,
        "EW_mean": 0.3748025670245655,
        "n_paths": 150
      },
      {
        "theta": 0.4,
        "age_ann": 58,
        "EU_mean": -4119248.1362549267,
        "EW_mean": 0.2848598237372304,
        "n_paths": 150
      },
      {
        "theta": 0.6,
        "age_ann": 58,
        "EU_mean": -4024369.065094104,
        "EW_mean": 0.1928757436206121,
        "n_paths": 150
      }
    ],
    "theta_star": 0.6
  },
  {
    "age_ann": 59,
    "results": [
      {
        "theta": 0.0,
        "age_ann": 59,
        "EU_mean": -4312056.408155986,
        "EW_mean": 0.46327406449248526,
        "n_paths": 150
      },
      {
        "theta": 0.2,
        "age_ann": 59,
        "EU_mean": -4207092.811677053,
        "EW_mean": 0.3746539186216877,
        "n_paths": 150
      },
      {
        "theta": 0.4,
        "age_ann": 59,
        "EU_mean": -4107357.9645067533,
        "EW_mean": 0.2846075465052126,
        "n_paths": 150
      },
      {
        "theta": 0.6,
        "age_ann": 59,
        "EU_mean": -4007608.4718759027,
        "EW_mean": 0.1925905833288755,
        "n_paths": 150
      }
    ],
    "theta_star": 0.6
  },
  {
    "age_ann": 60,
    "results": [
      {
        "theta": 0.0,
        "age_ann": 60,
        "EU_mean": -4312056.408155986,
        "EW_mean": 0.46327406449248526,
        "n_paths": 150
      },
      {
        "theta": 0.2,
        "age_ann": 60,
        "EU_mean": -4209352.609347298,
        "EW_mean": 0.37450782312763775,
        "n_paths": 150
      },
      {
        "theta": 0.4,
        "age_ann": 60,
        "EU_mean": -4111139.7883093585,
        "EW_mean": 0.2843597049091639,
        "n_paths": 150
      },
      {
        "theta": 0.6,
        "age_ann": 60,
        "EU_mean": -4013415.338234605,
        "EW_mean": 0.19231060516833315,
        "n_paths": 150
      }
    ],
    "theta_star": 0.6
  },
  {
    "age_ann": 61,
    "results": [
      {
        "theta": 0.0,
        "age_ann": 61,
        "EU_mean": -4312056.408155986,
        "EW_mean": 0.46327406449248526,
        "n_paths": 150
      },
      {
        "theta": 0.2,
        "age_ann": 61,
        "EU_mean": -4212095.835079007,
        "EW_mean": 0.37435803225088327,
        "n_paths": 150
      },
      {
        "theta": 0.4,
        "age_ann": 61,
        "EU_mean": -4117199.217849096,
        "EW_mean": 0.28410567290322203,
        "n_paths": 150
      },
      {
        "theta": 0.6,
        "age_ann": 61,
        "EU_mean": -4024216.2759318734,
        "EW_mean": 0.1920237616200888,
        "n_paths": 150
      }
    ],
    "theta_star": 0.6
  },
  {
    "age_ann": 62,
    "results": [
      {
        "theta": 0.0,
        "age_ann": 62,
        "EU_mean": -4312056.408155986,
        "EW_mean": 0.46327406449248526,
        "n_paths": 150
      },
      {
        "theta": 0.2,
        "age_ann": 62,
        "EU_mean": -4220640.661545539,
        "EW_mean": 0.3742119883259134,
        "n_paths": 150
      },
      {
        "theta": 0.4,
        "age_ann": 62,
        "EU_mean": -4134129.64613327,
        "EW_mean": 0.2838589400930191,
        "n_paths": 150
      },
      {
        "theta": 0.6,
        "age_ann": 62,
        "EU_mean": -4050288.6165962904,
        "EW_mean": 0.19174628919683107,
        "n_paths": 150
      }
    ],
    "theta_star": 0.6
  },
  {
    "age_ann": 63,
    "results": [
      {
        "theta": 0.0,
        "age_ann": 63,
        "EU_mean": -4312056.408155986,
        "EW_mean": 0.46327406449248526,
        "n_paths": 150
      },
      {
        "theta": 0.2,
        "age_ann": 63,
        "EU_mean": -4237042.950196528,
        "EW_mean": 0.3740586416567167,
        "n_paths": 150
      },
      {
        "theta": 0.4,
        "age_ann": 63,
        "EU_mean": -4166251.631920379,
        "EW_mean": 0.28360027346186,
        "n_paths": 150
      },
      {
        "theta": 0.6,
        "age_ann": 63,
        "EU_mean": -4098189.148532953,
        "EW_mean": 0.19145584801900611,
        "n_paths": 150
      }
    ],
    "theta_star": 0.6
  },
  {
    "age_ann": 64,
    "results": [
      {
        "theta": 0.0,
        "age_ann": 64,
        "EU_mean": -4312056.408155986,
        "EW_mean": 0.46327406449248526,
        "n_paths": 150
      },
      {
        "theta": 0.2,
        "age_ann": 64,
        "EU_mean": -4254286.887346672,
        "EW_mean": 0.37392114206947685,
        "n_paths": 150
      },
      {
        "theta": 0.4,
        "age_ann": 64,
        "EU_mean": -4200638.9522463,
        "EW_mean": 0.28336911627084554,
        "n_paths": 150
      },
      {
        "theta": 0.6,
        "age_ann": 64,
        "EU_mean": -4150096.1809997726,
        "EW_mean": 0.19119723542238484,
        "n_paths": 150
      }
    ],
    "theta_star": 0.6
  },
  {
    "age_ann": 65,
    "results": [
      {
        "theta": 0.0,
        "age_ann": 65,
        "EU_mean": -4312056.408155986,
        "EW_mean": 0.46327406449248526,
        "n_paths": 150
      },
      {
        "theta": 0.2,
        "age_ann": 65,
        "EU_mean": -4276733.51900438,
        "EW_mean": 0.3737627677606867,
        "n_paths": 150
      },
      {
        "theta": 0.4,
        "age_ann": 65,
        "EU_mean": -4244730.108468882,
        "EW_mean": 0.2831018931741545,
        "n_paths": 150
      },
      {
        "theta": 0.6,
        "age_ann": 65,
        "EU_mean": -4215416.228197776,
        "EW_mean": 0.1908971603108716,
        "n_paths": 150
      }
    ],
    "theta_star": 0.6
  }
]